leggen/__init__.py
leggen/api_client.py
leggen/main.py
leggen/api/dependencies.py
leggen/api/models/accounts.py
leggen/api/models/backup.py
leggen/api/models/banks.py
leggen/api/models/common.py
leggen/api/models/notifications.py
leggen/api/models/sync.py
leggen/api/routes/accounts.py
leggen/api/routes/backup.py
leggen/api/routes/banks.py
leggen/api/routes/notifications.py
leggen/api/routes/sync.py
leggen/api/routes/transactions.py
leggen/background/scheduler.py
leggen/commands/balances.py
leggen/commands/generate_sample_db.py
leggen/commands/server.py
leggen/commands/status.py
leggen/commands/sync.py
leggen/commands/transactions.py
leggen/commands/bank/add.py
leggen/commands/bank/delete.py
leggen/models/config.py
leggen/notifications/discord.py
leggen/notifications/telegram.py
leggen/repositories/__init__.py
leggen/repositories/account_repository.py
leggen/repositories/balance_repository.py
leggen/repositories/base_repository.py
leggen/repositories/migration_repository.py
leggen/repositories/sync_repository.py
leggen/repositories/transaction_repository.py
leggen/services/backup_service.py
leggen/services/database_service.py
leggen/services/gocardless_service.py
leggen/services/notification_service.py
leggen/services/sync_service.py
leggen/services/data_processors/__init__.py
leggen/services/data_processors/account_enricher.py
leggen/services/data_processors/analytics_processor.py
leggen/services/data_processors/balance_transformer.py
leggen/services/data_processors/transaction_processor.py
leggen/utils/config.py
leggen/utils/disk.py
leggen/utils/gocardless.py
leggen/utils/notifications.py
leggen/utils/paths.py
leggen/utils/text.py
leggen-2026.1.0.dist-info/METADATA
leggen-2026.1.0.dist-info/WHEEL
leggen-2026.1.0.dist-info/entry_points.txt
leggen-2026.1.0.dist-info/licenses/LICENSE
leggen-2026.1.0.dist-info/RECORD
