Metadata-Version: 2.4
Name: leggen
Version: 2026.1.0
Summary: An Open Banking CLI
Project-URL: Repository, https://github.com/elisiariocouto/leggen
Author-email: Elisiário Couto <elisiario@couto.io>
License-Expression: MIT
License-File: LICENSE
Keywords: bank,cli,finance,gocardless,openbanking,psd2,transactions
Classifier: Development Status :: 3 - Alpha
Classifier: Environment :: Console
Classifier: Intended Audience :: End Users/Desktop
Classifier: Intended Audience :: Financial and Insurance Industry
Classifier: Topic :: Office/Business :: Financial
Classifier: Topic :: Utilities
Requires-Python: ~=3.13.0
Requires-Dist: apscheduler<4,>=3.10.0
Requires-Dist: boto3<2,>=1.35.0
Requires-Dist: click<9,>=8.1.7
Requires-Dist: discord-webhook<2,>=1.3.1
Requires-Dist: fastapi<1,>=0.104.0
Requires-Dist: httpx>=0.28.1
Requires-Dist: loguru<0.8,>=0.7.2
Requires-Dist: pydantic<3,>=2.0.0
Requires-Dist: requests<3,>=2.31.0
Requires-Dist: tabulate<0.10,>=0.9.0
Requires-Dist: tomli-w<2,>=1.0.0
Requires-Dist: uvicorn[standard]<1,>=0.24.0
